Chinese2025/Error.py
Chinese2025/FanFangYan.py
Chinese2025/FanGuangYun.py
Chinese2025/FanNiYin.py
Chinese2025/FanPingShuiYun.py
Chinese2025/FanYongMingTi.py
Chinese2025/Unicode.py
Chinese2025/XianDaiYun.py
Chinese2025/ZhuShi.py
Chinese2025/__init__.py
Chinese2025/reconstructions_list.sqlite
Chinese2025/全局变量.py
Chinese2025/查询.py
Chinese2025/注释.py
Chinese2025/现代韵书搜索.py
Chinese2025/繁體平水韻搜索.py
Chinese2025/繁體廣韻搜索.py
Chinese2025/繁體擬音搜索.py
Chinese2025/繁體方言搜索.py
Chinese2025/繁體永明躰檢測.py
chinese2025-1.2.0.post2.dist-info/licenses/LICENSE
chinese2025-1.2.0.post2.dist-info/METADATA
chinese2025-1.2.0.post2.dist-info/WHEEL
chinese2025-1.2.0.post2.dist-info/top_level.txt
chinese2025-1.2.0.post2.dist-info/RECORD
